githooks/__init__.py
githooks/base_check.py
githooks/checks.py
githooks/commit_checks.py
githooks/commit_list_checks.py
githooks/config.py
githooks/file_checks.py
githooks/git.py
githooks/log_utils.py
githooks/utils.py
xt_githooks-0.4.3.dist-info/LICENSE
xt_githooks-0.4.3.dist-info/METADATA
xt_githooks-0.4.3.dist-info/WHEEL
xt_githooks-0.4.3.dist-info/entry_points.txt
xt_githooks-0.4.3.dist-info/top_level.txt
xt_githooks-0.4.3.dist-info/RECORD
